openai_requests_utils/__init__.py
openai_requests_utils/utils.py
openai_requests_utils-0.0.8.dist-info/LICENSE
openai_requests_utils-0.0.8.dist-info/METADATA
openai_requests_utils-0.0.8.dist-info/WHEEL
openai_requests_utils-0.0.8.dist-info/top_level.txt
openai_requests_utils-0.0.8.dist-info/RECORD
