Metadata-Version: 2.1
Name: openai_requests_utils
Version: 0.0.8
Summary: Useful utils to use with openai models
Author-email: Example Author <author@example.com>
Classifier: Programming Language :: Python :: 3
Classifier: License :: OSI Approved :: MIT License
Classifier: Operating System :: OS Independent
Requires-Python: >=3.8
License-File: LICENSE
